opencvv/__init__.py
opencvv/text_reader.py
opencvv/data/my_code.py
opencvv-0.3.dist-info/METADATA
opencvv-0.3.dist-info/WHEEL
opencvv-0.3.dist-info/top_level.txt
opencvv-0.3.dist-info/RECORD
