Metadata-Version: 2.1
Name: opencvv
Version: 0.3
Summary: Code for IPCV
Home-page: https://github.com/
Author: cockroachwater42
Author-email: cockroachwater42@gmail.com
License: UNKNOWN
Platform: UNKNOWN
